nvision/__init__.py
nvision/example.py
nvision/nvision.py
nvision-1.5.0.dist-info/DESCRIPTION.rst
nvision-1.5.0.dist-info/METADATA
nvision-1.5.0.dist-info/RECORD
nvision-1.5.0.dist-info/WHEEL
nvision-1.5.0.dist-info/metadata.json
nvision-1.5.0.dist-info/top_level.txt
