Metadata-Version: 2.0
Name: nvision
Version: 1.5.0
Summary: Nipa Cloud Platform: Nvision Python SDK
Home-page: https://github.com/nipa-cloud/nvision-python
Author: Nipa Cloud Platform
Author-email: devr@nipa.cloud
License: UNKNOWN
Keywords: Machine Learning,Deep Learning,Computer Vision,Nipa Cloud Service
Platform: UNKNOWN
Classifier: Programming Language :: Python :: 3
Classifier: Programming Language :: Python :: 3.5
Classifier: Programming Language :: Python :: 3.6
Classifier: Programming Language :: Python :: 3.7
Classifier: License :: OSI Approved :: Apache Software License
Classifier: Intended Audience :: Developers
Requires-Python: >=3.5
Requires-Dist: requests (>=2.22.0)
Requires-Dist: numpy (>=1.18.1)
Requires-Dist: bleach (>=2.1.0)
